djpaypal/__init__.py
djpaypal/admin.py
djpaypal/checks.py
djpaypal/enums.py
djpaypal/exceptions.py
djpaypal/fields.py
djpaypal/management/__init__.py
djpaypal/management/commands/__init__.py
djpaypal/management/commands/djpaypal_delete_all_test_data.py
djpaypal/management/commands/djpaypal_download_plans.py
djpaypal/management/commands/djpaypal_upload_plans.py
djpaypal/migrations/0001_initial.py
djpaypal/migrations/0002_payer_time_created.py
djpaypal/migrations/0003_auto_20180320_0902.py
djpaypal/migrations/0004_auto_20180323_2137.py
djpaypal/migrations/0005_auto_20180919_1447.py
djpaypal/migrations/0006_auto_20181001_1147.py
djpaypal/migrations/0007_sale_invoice_number.py
djpaypal/migrations/0008_refund_refund_to_payer.py
djpaypal/migrations/0009_shipping_address_null.py
djpaypal/migrations/0010_payment_hold.py
djpaypal/migrations/0011_disputes.py
djpaypal/migrations/0012_billing_agreement_state.py
djpaypal/migrations/0013_billing_agreement_plan_model.py
djpaypal/migrations/0014_use_models_jsonfield.py
djpaypal/migrations/__init__.py
djpaypal/models/__init__.py
djpaypal/models/base.py
djpaypal/models/billing.py
djpaypal/models/disputes.py
djpaypal/models/payer.py
djpaypal/models/payments.py
djpaypal/models/webhooks.py
djpaypal/settings.py
djpaypal/templates/djpaypal/admin/change_form.html
djpaypal/utils.py
djpaypal/views.py
dj_paypal-0.16.1.dist-info/LICENSE
dj_paypal-0.16.1.dist-info/METADATA
dj_paypal-0.16.1.dist-info/WHEEL
dj_paypal-0.16.1.dist-info/RECORD
