Metadata-Version: 2.3
Name: dj-paypal
Version: 0.16.1
Summary: Django / Paypal integration (based on dj-stripe)
Keywords: django,paypal,payments
Author: Benedict Etzel
Requires-Python: >=3.8,<4.0
Classifier: Development Status :: 5 - Production/Stable
Classifier: Environment :: Web Environment
Classifier: Framework :: Django
Classifier: Framework :: Django :: 3.1
Classifier: Intended Audience :: Developers
Classifier: License :: OSI Approved :: MIT License
Classifier: Programming Language :: Python :: 3
Classifier: Programming Language :: Python :: 3.8
Classifier: Programming Language :: Python :: 3.9
Classifier: Programming Language :: Python :: 3.10
Classifier: Programming Language :: Python :: 3.11
Classifier: Programming Language :: Python :: 3.12
Classifier: Programming Language :: Python :: 3.13
Classifier: Topic :: Office/Business :: Financial
Classifier: Topic :: Software Development :: Libraries :: Python Modules
Requires-Dist: django (>=3.1)
Requires-Dist: paypalrestsdk (>=1.13.1)
Requires-Dist: python-dateutil (>=2.6.1)
Project-URL: Repository, https://github.com/dj-stripe/dj-paypal
